[{"date":"2020/02/15","deaths":"0","cases":"8"},{"date":"2020/02/16","deaths":"0","cases":"8"},{"date":"2020/02/17","deaths":"0","cases":"8"},{"date":"2020/02/18","deaths":"0","cases":"8"},{"date":"2020/02/19","deaths":"0","cases":"8"},{"date":"2020/02/20","deaths":"0","cases":"8"},{"date":"2020/02/21","deaths":"0","cases":"8"},{"date":"2020/02/22","deaths":"0","cases":"9"},{"date":"2020/02/23","deaths":"0","cases":"9"},{"date":"2020/02/24","deaths":"0","cases":"10"},{"date":"2020/02/25","deaths":"0","cases":"11"},{"date":"2020/02/26","deaths":"0","cases":"12"},{"date":"2020/02/27","deaths":"0","cases":"14"},{"date":"2020/02/28","deaths":"0","cases":"15"},{"date":"2020/02/29","deaths":"0","cases":"20"},{"date":"2020/03/01","deaths":"0","cases":"24"},{"date":"2020/03/02","deaths":"0","cases":"27"},{"date":"2020/03/03","deaths":"0","cases":"30"},{"date":"2020/03/04","deaths":"0","cases":"34"},{"date":"2020/03/05","deaths":"0","cases":"37"},{"date":"2020/03/06","deaths":"0","cases":"54"},{"date":"2020/03/07","deaths":"0","cases":"60"},{"date":"2020/03/08","deaths":"0","cases":"66"},{"date":"2020/03/09","deaths":"1","cases":"77"},{"date":"2020/03/10","deaths":"1","cases":"95"},{"date":"2020/03/11","deaths":"1","cases":"110"},{"date":"2020/03/12","deaths":"1","cases":"142"},{"date":"2020/03/13","deaths":"1","cases":"198"},{"date":"2020/03/14","deaths":"1","cases":"252"},{"date":"2020/03/15","deaths":"1","cases":"341"},{"date":"2020/03/16","deaths":"4","cases":"441"},{"date":"2020/03/17","deaths":"8","cases":"598"},{"date":"2020/03/18","deaths":"9","cases":"727"},{"date":"2020/03/19","deaths":"12","cases":"873"},{"date":"2020/03/20","deaths":"12","cases":"1087"},{"date":"2020/03/21","deaths":"19","cases":"1328"},{"date":"2020/03/22","deaths":"20","cases":"1470"},{"date":"2020/03/23","deaths":"24","cases":"2091"},{"date":"2020/03/24","deaths":"26","cases":"2792"},{"date":"2020/03/25","deaths":"36","cases":"3409"},{"date":"2020/03/26","deaths":"39","cases":"4043"},{"date":"2020/03/27","deaths":"55","cases":"4757"},{"date":"2020/03/28","deaths":"60","cases":"5665"},{"date":"2020/03/29","deaths":"65","cases":"6320"},{"date":"2020/03/30","deaths":"89","cases":"7448"},{"date":"2020/03/31","deaths":"101","cases":"8612"},{"date":"2020/04/01","deaths":"114","cases":"9731"},{"date":"2020/04/02","deaths":"173","cases":"11283"},{"date":"2020/04/03","deaths":"208","cases":"12375"},{"date":"2020/04/04","deaths":"231","cases":"13912"},{"date":"2020/04/05","deaths":"280","cases":"15512"},{"date":"2020/04/06","cases":"16498","deaths":"321"},{"date":"2020/04/07","cases":"17897","deaths":"381"},{"date":"2020/04/08","cases":"19438","deaths":"427"},{"date":"2020/04/09","cases":"+4799","deaths":"+1341"}]